koaviewer/__init__.py
koaviewer/viewer.py
koaviewer/data/app.css
koaviewer/data/bump.js
koaviewer/data/dashAgGridComponentFunctions.js
koaviewer/data/koa.css
koaviewer/data/panes.js
koaviewer/data/style.css
koaviewer-1.0.2.dist-info/licenses/LICENSE
koaviewer-1.0.2.dist-info/METADATA
koaviewer-1.0.2.dist-info/WHEEL
koaviewer-1.0.2.dist-info/top_level.txt
koaviewer-1.0.2.dist-info/RECORD
