Metadata-Version: 2.4
Name: koaviewer
Version: 1.0.2
Summary: Astronomical image display and interaction.
Author-email: John Good <jcg@caltech.edu>
License-Expression: BSD-3-Clause
Project-URL: Homepage, https://koa.ipac.caltech/edu
Requires-Python: >=3.6
License-File: LICENSE
Requires-Dist: pandas
Requires-Dist: astropy
Requires-Dist: pillow
Requires-Dist: dash
Requires-Dist: dash_bootstrap_components
Requires-Dist: dash_ag_grid
Requires-Dist: MontagePy
Requires-Dist: mviewer
Dynamic: license-file
